setup.py
Flask_MultipleBlueprint.egg-info/PKG-INFO
Flask_MultipleBlueprint.egg-info/SOURCES.txt
Flask_MultipleBlueprint.egg-info/dependency_links.txt
Flask_MultipleBlueprint.egg-info/requires.txt
Flask_MultipleBlueprint.egg-info/top_level.txt
flask_multipleblueprint/__init__.py
flask_multipleblueprint/multipleblueprint.py