Metadata-Version: 1.1
Name: Flask-MultipleBlueprint
Version: 0.1
Summary: Decorate function using multiple blueprints at once.
Home-page: UNKNOWN
Author: Cha, Hojeong
Author-email: ikadro+flask@gmail.com
License: MIT License
Platform: UNKNOWN
Classifier: Development Status :: 4 - Beta
Classifier: Intended Audience :: Developers
Classifier: License :: OSI Approved :: MIT License
Classifier: Operating System :: OS Independent
Classifier: Programming Language :: Python :: 2.7
Classifier: Programming Language :: Python :: Implementation :: CPython
Classifier: Topic :: Internet :: WWW/HTTP :: Dynamic Content
Classifier: Topic :: Software Development :: Libraries :: Python Modules
